chronoflow/__init__.py
chronoflow/main.py
chronoflow/datetime/__init__.py
chronoflow/datetime/main.py
chronoflow/ginter/__init__.py
chronoflow/ginter/main.py
chronoflow-0.4.dist-info/METADATA
chronoflow-0.4.dist-info/WHEEL
chronoflow-0.4.dist-info/top_level.txt
chronoflow-0.4.dist-info/RECORD
